{"cameraMode":{"drawMode":0,"name":"Shaded","section":"Shading Mode"},"sceneLighting":true,"audioPlay":false,"sceneViewState":{"showFog":true,"showMaterialUpdate":false,"showSkybox":true,"showFlares":true,"showImageEffects":true,"showParticleSystems":true},"in2DMode":false,"pivot":{"x":1.8443162441253663,"y":0.34448468685150149,"z":-0.8047964572906494},"rotation":{"x":-0.07009974867105484,"y":0.03859224170446396,"z":-0.00271386606618762,"w":-0.9967899322509766},"size":6.790411949157715,"orthographic":false}